webuuid/__init__.py
webuuid/codecs.py
webuuid/py.typed
webuuid-0.1.2.dist-info/LICENSE
webuuid-0.1.2.dist-info/WHEEL
webuuid-0.1.2.dist-info/METADATA
webuuid-0.1.2.dist-info/RECORD
