Metadata-Version: 2.1
Name: webuuid
Version: 0.1.2
Summary: Optimize UUID for web services
Home-page: https://github.com/JGoutin/webuuid
License: BSD-2-Clause
Keywords: uuid,uuid6,uuid7,pydantic,fastapi
Author: JGoutin
Requires-Python: >=3.8,<4.0
Classifier: Development Status :: 4 - Beta
Classifier: Intended Audience :: Developers
Classifier: License :: OSI Approved :: BSD License
Classifier: Programming Language :: Python :: 3
Classifier: Programming Language :: Python :: 3.8
Classifier: Programming Language :: Python :: 3.9
Classifier: Programming Language :: Python :: 3.10
Classifier: Programming Language :: Python :: 3.11
Classifier: Typing :: Typed
Project-URL: Repository, https://github.com/JGoutin/webuuid
